cdiutils/__init__.py
cdiutils/converter.py
cdiutils/geometry.py
cdiutils/utils.py
cdiutils/wavefront.py
cdiutils/analysis/__init__.py
cdiutils/analysis/stats.py
cdiutils/analysis/stereography.py
cdiutils/facetanalysis/facet_correlation.py
cdiutils/facetanalysis/facet_utils.py
cdiutils/facetanalysis/get_facet_data.py
cdiutils/io/__init__.py
cdiutils/io/cristal.py
cdiutils/io/cxi.py
cdiutils/io/cxi_explorer.py
cdiutils/io/id01.py
cdiutils/io/id27.py
cdiutils/io/loader.py
cdiutils/io/nanomax.py
cdiutils/io/p10.py
cdiutils/io/sixs.py
cdiutils/io/vtk.py
cdiutils/multibcdi/3D_phase.py
cdiutils/multibcdi/__init__.py
cdiutils/multibcdi/preprocess.py
cdiutils/pipeline/__init__.py
cdiutils/pipeline/base.py
cdiutils/pipeline/bcdi.py
cdiutils/pipeline/parameters.py
cdiutils/pipeline/pipeline_plotter.py
cdiutils/pipeline/pynx-id01-cdi_template.slurm
cdiutils/plot/__init__.py
cdiutils/plot/colormap.py
cdiutils/plot/formatting.py
cdiutils/plot/interactive.py
cdiutils/plot/quiver.py
cdiutils/plot/slice.py
cdiutils/plot/volume.py
cdiutils/process/__init__.py
cdiutils/process/facet_analysis.py
cdiutils/process/phaser.py
cdiutils/process/postprocessor.py
cdiutils/process/support_processor.py
cdiutils/scripts/__init__.py
cdiutils/scripts/prepare_bcdi_notebooks.py
cdiutils/scripts/prepare_detector_calibration.py
cdiutils/templates/bcdi_pipeline.ipynb
cdiutils/templates/detector_calibration.ipynb
cdiutils/templates/step_by_step_bcdi_analysis.ipynb
cdiutils-0.2.0.dist-info/licenses/LICENSE
cdiutils-0.2.0.dist-info/METADATA
cdiutils-0.2.0.dist-info/WHEEL
cdiutils-0.2.0.dist-info/entry_points.txt
cdiutils-0.2.0.dist-info/top_level.txt
cdiutils-0.2.0.dist-info/RECORD
