Metadata-Version: 2.4
Name: cdiutils
Version: 0.2.0
Summary: A Python package for (Bragg) Coherent X-ray Diffraction Imaging processing, analysis and visualisation workflows.
Author: Corentin Chatelier, David Simonne, Matthieu Deschamps, Kyle Olson
Author-email: Clement Atlan <clement.atlan@esrf.fr>
Maintainer-email: Clement Atlan <clement.atlan@esrf.fr>
License-Expression: MIT
Project-URL: Homepage, https://github.com/clatlan/cdiutils
Keywords: reconstruction,coherent X-ray imaging,Bragg,pipeline,synchrotron radiation,quantitative analysis
Requires-Python: >=3.10
License-File: LICENSE
Requires-Dist: colorcet>=3.0.0
Requires-Dist: h5py>=3.6.0
Requires-Dist: hdf5plugin>=3.2.0
Requires-Dist: ipykernel
Requires-Dist: matplotlib>=3.8
Requires-Dist: numpy
Requires-Dist: pandas>=1.4.2
Requires-Dist: scikit-image>=0.19.2
Requires-Dist: scikit-learn>=1.1.3
Requires-Dist: scipy>=1.8.0
Requires-Dist: seaborn>=0.12.1
Requires-Dist: silx
Requires-Dist: tabulate
Requires-Dist: xrayutilities>=1.7.3
Requires-Dist: ipyvolume
Requires-Dist: ipython_genutils
Requires-Dist: bokeh
Requires-Dist: panel
Requires-Dist: tornado
Provides-Extra: vtk
Requires-Dist: vtk>=9.0.1; extra == "vtk"
Dynamic: license-file
